netcdf_extraction_util/__init__.py
netcdf_extraction_util/command_line.py
netcdf_extraction_util/netcdf_extraction.py
netcdf_extraction_util-0.1.1.dist-info/LICENCE.txt
netcdf_extraction_util-0.1.1.dist-info/METADATA
netcdf_extraction_util-0.1.1.dist-info/WHEEL
netcdf_extraction_util-0.1.1.dist-info/entry_points.txt
netcdf_extraction_util-0.1.1.dist-info/top_level.txt
netcdf_extraction_util-0.1.1.dist-info/RECORD
