Metadata-Version: 2.1
Name: netcdf-extraction-util
Version: 0.1.1
Summary: Script to extract time-series from Netcdf
Home-page: https://github.com/daniel-lagrava-niwa/netcdf_extraction_util
Author: Daniel Lagrava
Author-email: daniel.lagravasandoval@niwa.co.nz
License: GNU
Platform: UNKNOWN
Requires-Dist: numpy
Requires-Dist: netCDF4
Requires-Dist: xarray
